cerebralcortex_rest/__init__.py
cerebralcortex_rest/client.py
cerebralcortex_restclient-3.3.0.dist-info/DESCRIPTION.rst
cerebralcortex_restclient-3.3.0.dist-info/METADATA
cerebralcortex_restclient-3.3.0.dist-info/RECORD
cerebralcortex_restclient-3.3.0.dist-info/WHEEL
cerebralcortex_restclient-3.3.0.dist-info/entry_points.txt
cerebralcortex_restclient-3.3.0.dist-info/metadata.json
cerebralcortex_restclient-3.3.0.dist-info/top_level.txt
