Metadata-Version: 2.0
Name: cerebralcortex-restclient
Version: 3.3.0
Summary: REST client for CerebralCortex-APIServer.
Home-page: https://github.com/MD2Korg/CerebralCortex-RESTClient/
Author: MD2K.org
Author-email: dev@md2k.org
License: BSD2
Keywords: mHealth machine-learning data-analysis
Platform: UNKNOWN
Classifier: Development Status :: 5 - Production/Stable
Classifier: Intended Audience :: Healthcare Industry
Classifier: Intended Audience :: Science/Research
Classifier: License :: OSI Approved :: BSD License
Classifier: Natural Language :: English
Classifier: Programming Language :: Python :: 3
Classifier: Topic :: Scientific/Engineering :: Information Analysis
Classifier: Topic :: System :: Distributed Computing
Requires-Dist: PyJWT (==1.7.1)
Requires-Dist: cerebralcortex-kernel (==3.3.0)
